xproj/__init__.py
xproj/accessor.py
xproj/crs_utils.py
xproj/index.py
xproj/mixins.py
xproj/typing.py
xproj/utils.py
xproj/tests/__init__.py
xproj/tests/test_3rdparty_accessor.py
xproj/tests/test_3rdparty_index.py
xproj/tests/test_accessor.py
xproj/tests/test_crs_utils.py
xproj/tests/test_index.py
xproj-0.2.1.dist-info/licenses/LICENSE
xproj-0.2.1.dist-info/METADATA
xproj-0.2.1.dist-info/WHEEL
xproj-0.2.1.dist-info/top_level.txt
xproj-0.2.1.dist-info/RECORD
