Metadata-Version: 2.4
Name: xproj
Version: 0.2.1
Summary: Xarray extension for projections and coordinate reference systems
Author: Benoît Bovy, Scott Henderson
Maintainer: xproj contributors
License: Apache-2.0
Project-URL: Documentation, https://xproj.readthedocs.io
Project-URL: Repository, https://github.com/xarray-contrib/xproj
Keywords: xarray,GIS,CRS,proj
Classifier: Intended Audience :: Science/Research
Classifier: License :: OSI Approved :: Apache Software License
Classifier: Operating System :: OS Independent
Classifier: Programming Language :: Python :: 3
Classifier: Topic :: Scientific/Engineering :: GIS
Requires-Python: >=3.10
License-File: LICENSE
Requires-Dist: xarray
Requires-Dist: pyproj
Provides-Extra: test
Requires-Dist: pytest; extra == "test"
Dynamic: license-file
